<?xml version="1.0" ?>
<Commands>
    <Command Name="jobwhitelist" Hash="2189523071" />
    <Command Name="bizdelflooritems" Hash="158748106" />
    <Command Name="bizpublic" Hash="2572551879" />
    <Command Name="returnplr" Hash="2563135004" />
    <Command Name="additemtype" Hash="1625056830" />
    <Command Name="say" Hash="4241071205" />
    <Command Name="freq" Hash="1475614133" />
    <Command Name="items" Hash="3776899405" />
    <Command Name="iplogin" Hash="3830114180" />
    <Command Name="exit" Hash="2483651598" />
    <Command Name="addjobrouteloc" Hash="2057882151" />
    <Command Name="houseentrance" Hash="1732577001" />
    <Command Name="houseclan" Hash="3573514699" />
    <Command Name="aban" Hash="1063339661" />
    <Command Name="vw" Hash="4141688848" />
    <Command Name="autolastchar" Hash="3186897000" />
    <Command Name="quit" Hash="1135269781" />
    <Command Name="notips" Hash="3711348993" />
    <Command Name="help" Hash="143088812" />
    <Command Name="equip" Hash="4067673008" />
    <Command Name="ccode" Hash="1323373828" />
    <Command Name="start" Hash="2675529103" />
    <Command Name="locale" Hash="1098958488" />
    <Command Name="restart" Hash="3891864071" />
    <Command Name="carrespawnclan" Hash="1840990743" />
    <Command Name="deljobroute" Hash="3139178648" />
    <Command Name="setemail" Hash="795930342" />
    <Command Name="reloadcfg" Hash="2937436470" />
    <Command Name="cmd" Hash="794565824" />
    <Command Name="vehreloadall" Hash="1958007921" />
    <Command Name="stopall" Hash="1683731152" />
    <Command Name="stop" Hash="3109426870" />
    <Command Name="refresh" Hash="1619108091" />
    <Command Name="bizjob" Hash="1623679964" />
    <Command Name="jobcolour" Hash="1906062370" />
    <Command Name="subnetban" Hash="3446702509" />
    <Command Name="bizdefaultitems" Hash="492108129" />
    <Command Name="dumpdoc" Hash="3404143852" />
    <Command Name="bizclan" Hash="2741917790" />
    <Command Name="bizdeposit" Hash="4085204187" />
    <Command Name="accent" Hash="1734464235" />
    <Command Name="streamnameall" Hash="257040269" />
    <Command Name="accents" Hash="749835561" />
    <Command Name="bizfloor" Hash="991723021" />
    <Command Name="bizowner" Hash="1245269599" />
    <Command Name="jobrouteenabled" Hash="2783446125" />
    <Command Name="bizreloadall" Hash="1391182304" />
    <Command Name="accentlist" Hash="1686860130" />
    <Command Name="login" Hash="2852702992" />
    <Command Name="mute" Hash="3434705756" />
    <Command Name="drop" Hash="1880425762" />
    <Command Name="register" Hash="1610170388" />
    <Command Name="bizstore" Hash="2047799380" />
    <Command Name="gotoveh" Hash="1314378666" />
    <Command Name="bizname" Hash="1656456532" />
    <Command Name="changepass" Hash="1379839939" />
    <Command Name="bizorder" Hash="1886403515" />
    <Command Name="anims" Hash="3889228819" />
    <Command Name="scrolllines" Hash="1527443730" />
    <Command Name="gui" Hash="3573502200" />
    <Command Name="2fa" Hash="3518788867" />
    <Command Name="verifyemail" Hash="3201570836" />
    <Command Name="loginalert" Hash="2359999903" />
    <Command Name="siren" Hash="3683367432" />
    <Command Name="mousecam" Hash="3206767913" />
    <Command Name="bizbuyprice" Hash="655960419" />
    <Command Name="delstaffflag" Hash="1313026715" />
    <Command Name="bizexit" Hash="2828107612" />
    <Command Name="chatautohide" Hash="4051244712" />
    <Command Name="newchar" Hash="4170498675" />
    <Command Name="anim" Hash="1739285595" />
    <Command Name="lights" Hash="951890664" />
    <Command Name="charban" Hash="994982700" />
    <Command Name="biztill" Hash="869001970" />
    <Command Name="an" Hash="2536834118" />
    <Command Name="e" Hash="4024072794" />
    <Command Name="addstaffflag" Hash="79289023" />
    <Command Name="animlist" Hash="2302640798" />
    <Command Name="vehjob" Hash="3344978244" />
    <Command Name="clanchat" Hash="3592644293" />
    <Command Name="stopanim" Hash="423975717" />
    <Command Name="houseexit" Hash="3741361865" />
    <Command Name="spawnveh" Hash="4087978827" />
    <Command Name="acctban" Hash="2579355258" />
    <Command Name="cban" Hash="2506657286" />
    <Command Name="delplritem" Hash="2217077700" />
    <Command Name="saban" Hash="1719006355" />
    <Command Name="ipban" Hash="2759871306" />
    <Command Name="delloglevel" Hash="3046139078" />
    <Command Name="addbiz" Hash="3844119303" />
    <Command Name="delbiz" Hash="1295584235" />
    <Command Name="bizlock" Hash="3138871388" />
    <Command Name="bizlights" Hash="2589891122" />
    <Command Name="bizbuy" Hash="1419510099" />
    <Command Name="addtrigresp" Hash="2942770628" />
    <Command Name="bizfee" Hash="223799185" />
    <Command Name="bizitemprice" Hash="3432680323" />
    <Command Name="bizbalance" Hash="3394291228" />
    <Command Name="bizstock" Hash="3463446083" />
    <Command Name="bizwithdraw" Hash="4223432723" />
    <Command Name="buy" Hash="3481502327" />
    <Command Name="bizdelowner" Hash="3491490727" />
    <Command Name="bizrank" Hash="3034649527" />
    <Command Name="bizblip" Hash="688162896" />
    <Command Name="bizpickup" Hash="3816558887" />
    <Command Name="bizinfo" Hash="4145138181" />
    <Command Name="cmdenabletype" Hash="3401887628" />
    <Command Name="bizflooritems" Hash="3152039807" />
    <Command Name="bizentrance" Hash="3384296964" />
    <Command Name="nosave" Hash="3967601367" />
    <Command Name="bizinttype" Hash="1993387962" />
    <Command Name="vehrespawnclan" Hash="2839312157" />
    <Command Name="bizdelstorageitems" Hash="640974901" />
    <Command Name="bizdealership" Hash="1448970834" />
    <Command Name="deljobrouteloc" Hash="630262577" />
    <Command Name="me" Hash="2891092674" />
    <Command Name="setgui" Hash="2722470096" />
    <Command Name="do" Hash="2638594197" />
    <Command Name="radioreloadall" Hash="240903479" />
    <Command Name="s" Hash="453955339" />
    <Command Name="shout" Hash="3228108389" />
    <Command Name="lock" Hash="2274335502" />
    <Command Name="setjobblips" Hash="3692573588" />
    <Command Name="talk" Hash="2669991355" />
    <Command Name="local" Hash="2346092776" />
    <Command Name="l" Hash="2517025534" />
    <Command Name="setlang" Hash="80385616" />
    <Command Name="testguiprompt" Hash="1276898732" />
    <Command Name="reloademailcfg" Hash="3863532754" />
    <Command Name="w" Hash="476252946" />
    <Command Name="gotobiz" Hash="175433282" />
    <Command Name="whisper" Hash="1339834624" />
    <Command Name="clan" Hash="2683740940" />
    <Command Name="jobroutestartmsg" Hash="3050645607" />
    <Command Name="addclan" Hash="4056447230" />
    <Command Name="c" Hash="112844655" />
    <Command Name="adminchat" Hash="1592899621" />
    <Command Name="admins" Hash="2732594447" />
    <Command Name="a" Hash="3904355907" />
    <Command Name="gotospawn" Hash="1617509273" />
    <Command Name="achat" Hash="648643670" />
    <Command Name="houseowner" Hash="3391862861" />
    <Command Name="m" Hash="3775001192" />
    <Command Name="clans" Hash="304575875" />
    <Command Name="testguierror" Hash="491890956" />
    <Command Name="clanranks" Hash="374891081" />
    <Command Name="clanflags" Hash="3602613223" />
    <Command Name="clearstaffflags" Hash="1933688633" />
    <Command Name="delclan" Hash="1490865981" />
    <Command Name="oldveh" Hash="2876867678" />
    <Command Name="nearveh" Hash="1881612975" />
    <Command Name="clanaddrank" Hash="2620943916" />
    <Command Name="stoproute" Hash="3037172349" />
    <Command Name="clandelrank" Hash="892131823" />
    <Command Name="clansetrank" Hash="3351619564" />
    <Command Name="clanowner" Hash="316548129" />
    <Command Name="clantag" Hash="3681023611" />
    <Command Name="clanranktag" Hash="1772177415" />
    <Command Name="clanmembertag" Hash="959912259" />
    <Command Name="clanrankname" Hash="3030127040" />
    <Command Name="clanranklevel" Hash="3892778233" />
    <Command Name="clanmembertitle" Hash="3517062004" />
    <Command Name="getplrveh" Hash="3278782420" />
    <Command Name="clanaddrankflag" Hash="2541715106" />
    <Command Name="clanrankflags" Hash="2045286736" />
    <Command Name="clandelrankflag" Hash="2989628358" />
    <Command Name="clanaddmemberflag" Hash="2650664065" />
    <Command Name="clandelmemberflag" Hash="2712990392" />
    <Command Name="armour" Hash="2549936275" />
    <Command Name="cmddisabletype" Hash="3293268402" />
    <Command Name="bindkey" Hash="1227425763" />
    <Command Name="cmdenable" Hash="4119993794" />
    <Command Name="cmddisable" Hash="4076768664" />
    <Command Name="jobblip" Hash="2619537769" />
    <Command Name="settime" Hash="1515686519" />
    <Command Name="setminuteduration" Hash="3347405783" />
    <Command Name="jobroutelocarrivemsg" Hash="2806715855" />
    <Command Name="setweather" Hash="296092028" />
    <Command Name="setsnow" Hash="54572929" />
    <Command Name="setlogo" Hash="3511519265" />
    <Command Name="setguicolours" Hash="1253001477" />
    <Command Name="newcharspawn" Hash="3561425132" />
    <Command Name="newcharcash" Hash="1263771093" />
    <Command Name="addgrounditem" Hash="766381040" />
    <Command Name="newcharskin" Hash="1335038066" />
    <Command Name="vehrespawnempty" Hash="37869538" />
    <Command Name="reloaddbcfg" Hash="2688744694" />
    <Command Name="reloadlocalecfg" Hash="3323883086" />
    <Command Name="reloadaccentcfg" Hash="1762311642" />
    <Command Name="setbizblips" Hash="2208865773" />
    <Command Name="docmdall" Hash="3550628791" />
    <Command Name="sethouseblips" Hash="3851708594" />
    <Command Name="bizstorage" Hash="853459670" />
    <Command Name="setbizpickups" Hash="2871853734" />
    <Command Name="sethousepickups" Hash="1540957074" />
    <Command Name="kick" Hash="517332741" />
    <Command Name="setjobpickups" Hash="1690177862" />
    <Command Name="dbquery" Hash="1161190191" />
    <Command Name="scode" Hash="771850886" />
    <Command Name="gmx" Hash="1012197459" />
    <Command Name="rt" Hash="196656302" />
    <Command Name="saveall" Hash="1031238566" />
    <Command Name="docmd" Hash="432538647" />
    <Command Name="addloglevel" Hash="2430402978" />
    <Command Name="loglevel" Hash="3600896637" />
    <Command Name="streamurlall" Hash="432433149" />
    <Command Name="forceresetpass" Hash="2586824369" />
    <Command Name="fixblips" Hash="3117299078" />
    <Command Name="fixpickups" Hash="4113146230" />
    <Command Name="carrespawnbiz" Hash="2668944323" />
    <Command Name="cars" Hash="2512854292" />
    <Command Name="resetambience" Hash="2196473743" />
    <Command Name="testguiinfo" Hash="2560043709" />
    <Command Name="jobroutefinishmsg" Hash="4059033309" />
    <Command Name="tax" Hash="2390866550" />
    <Command Name="wealth" Hash="1012568925" />
    <Command Name="givemoney" Hash="3084115026" />
    <Command Name="forcepayday" Hash="152293771" />
    <Command Name="speak" Hash="4227147363" />
    <Command Name="testemail" Hash="3217958560" />
    <Command Name="commands" Hash="2587759404" />
    <Command Name="enter" Hash="3111174254" />
    <Command Name="cmds" Hash="2152026535" />
    <Command Name="info" Hash="3414765911" />
    <Command Name="pos" Hash="2161764012" />
    <Command Name="veh" Hash="4108237688" />
    <Command Name="warpinveh" Hash="1511727410" />
    <Command Name="v" Hash="1801730948" />
    <Command Name="car" Hash="2000545437" />
    <Command Name="spawncar" Hash="1883948718" />
    <Command Name="skin" Hash="41510942" />
    <Command Name="vehdelowner" Hash="1446958743" />
    <Command Name="trigresp" Hash="3910880795" />
    <Command Name="skins" Hash="3775105792" />
    <Command Name="addjobloc" Hash="3531129112" />
    <Command Name="clothes" Hash="813282444" />
    <Command Name="changeskin" Hash="2654409721" />
    <Command Name="addhouse" Hash="872977526" />
    <Command Name="delhouse" Hash="919344075" />
    <Command Name="take" Hash="937258619" />
    <Command Name="housereloadall" Hash="2365497957" />
    <Command Name="getveh" Hash="438514653" />
    <Command Name="quitjob" Hash="4168778638" />
    <Command Name="houseinfo" Hash="2155877264" />
    <Command Name="engine" Hash="3903330957" />
    <Command Name="addtrigcond" Hash="2950893705" />
    <Command Name="geoip" Hash="1182365374" />
    <Command Name="housebuy" Hash="3262448210" />
    <Command Name="addveh" Hash="2701373167" />
    <Command Name="housedesc" Hash="1086099091" />
    <Command Name="cursor" Hash="3313461902" />
    <Command Name="houselock" Hash="3431381449" />
    <Command Name="houselights" Hash="1768421772" />
    <Command Name="drag" Hash="1833282923" />
    <Command Name="housebuyprice" Hash="2313447822" />
    <Command Name="up" Hash="1133833840" />
    <Command Name="houserentprice" Hash="2866086582" />
    <Command Name="houseblip" Hash="1586844101" />
    <Command Name="gps" Hash="1424645575" />
    <Command Name="housepickup" Hash="272986777" />
    <Command Name="houseinttype" Hash="1526335570" />
    <Command Name="i" Hash="3865851505" />
    <Command Name="item" Hash="521872670" />
    <Command Name="additem" Hash="1898315500" />
    <Command Name="delgrounditem" Hash="300357065" />
    <Command Name="delplritems" Hash="2273569865" />
    <Command Name="itemtypeuseval" Hash="4115341070" />
    <Command Name="pickup" Hash="1100888573" />
    <Command Name="put" Hash="2928708052" />
    <Command Name="inventory" Hash="2972535350" />
    <Command Name="use" Hash="2494680139" />
    <Command Name="inv" Hash="4200577949" />
    <Command Name="houseitems" Hash="3830822780" />
    <Command Name="buylist" Hash="1273281402" />
    <Command Name="vehbuyprice" Hash="2705069139" />
    <Command Name="power" Hash="2877948320" />
    <Command Name="radio" Hash="3762690831" />
    <Command Name="r" Hash="1812594589" />
    <Command Name="itemtypeusetype" Hash="1457290076" />
    <Command Name="itemtypeorderprice" Hash="1622827053" />
    <Command Name="itemtyperiskmult" Hash="298256682" />
    <Command Name="itemtypeenabled" Hash="1424486221" />
    <Command Name="jobaddplayerbl" Hash="3037502154" />
    <Command Name="takejob" Hash="2690682686" />
    <Command Name="startwork" Hash="307130076" />
    <Command Name="setstars" Hash="3388953278" />
    <Command Name="stopwork" Hash="765483006" />
    <Command Name="health" Hash="3470402323" />
    <Command Name="startjob" Hash="4288994387" />
    <Command Name="stopjob" Hash="2761630709" />
    <Command Name="uniform" Hash="4130109879" />
    <Command Name="passenger" Hash="1005578461" />
    <Command Name="department" Hash="3441287562" />
    <Command Name="d" Hash="2564639436" />
    <Command Name="delveh" Hash="152714755" />
    <Command Name="fare" Hash="1456298103" />
    <Command Name="detain" Hash="3221757631" />
    <Command Name="search" Hash="3035683751" />
    <Command Name="startroute" Hash="1616395680" />
    <Command Name="jobbl" Hash="779699388" />
    <Command Name="addjob" Hash="2919626095" />
    <Command Name="deljobloc" Hash="1739246254" />
    <Command Name="addjobroute" Hash="2656138748" />
    <Command Name="jobtoggle" Hash="2928606311" />
    <Command Name="jobroutename" Hash="2017870989" />
    <Command Name="jobroutepay" Hash="1116013836" />
    <Command Name="jobroutelocnextmsg" Hash="1672851411" />
    <Command Name="jobroutevehcolours" Hash="1488821428" />
    <Command Name="jobroutedelays" Hash="1645912336" />
    <Command Name="jobpickup" Hash="3405408273" />
    <Command Name="jobwl" Hash="432841384" />
    <Command Name="jobblacklist" Hash="1922085790" />
    <Command Name="freeze" Hash="1183970330" />
    <Command Name="radiostations" Hash="3940254175" />
    <Command Name="jobaddplayerwl" Hash="2193194206" />
    <Command Name="jobdelplayerbl" Hash="2420244398" />
    <Command Name="jobreloadall" Hash="2284567617" />
    <Command Name="jobinfo" Hash="1110948668" />
    <Command Name="vehpublic" Hash="3482619154" />
    <Command Name="joblocinfo" Hash="3048238516" />
    <Command Name="unbindkey" Hash="1293547552" />
    <Command Name="keybinds" Hash="839428196" />
    <Command Name="lang" Hash="822707298" />
    <Command Name="language" Hash="3571151285" />
    <Command Name="idea" Hash="176933445" />
    <Command Name="bug" Hash="898416404" />
    <Command Name="yes" Hash="1978086825" />
    <Command Name="no" Hash="1739204639" />
    <Command Name="stuck" Hash="1518825670" />
    <Command Name="radiostation" Hash="28088017" />
    <Command Name="radiovolume" Hash="1214320345" />
    <Command Name="unmute" Hash="567433405" />
    <Command Name="infiniterun" Hash="872561642" />
    <Command Name="unfreeze" Hash="2907185820" />
    <Command Name="goto" Hash="1382046848" />
    <Command Name="gethere" Hash="390671735" />
    <Command Name="vehinfo" Hash="157447745" />
    <Command Name="gotopos" Hash="978357886" />
    <Command Name="lastveh" Hash="1130556078" />
    <Command Name="gotohouse" Hash="2545077731" />
    <Command Name="gotojob" Hash="1095862314" />
    <Command Name="gotoloc" Hash="853263374" />
    <Command Name="fr" Hash="3430272718" />
    <Command Name="ba" Hash="749160980" />
    <Command Name="lt" Hash="3757671281" />
    <Command Name="vehrentprice" Hash="1386181794" />
    <Command Name="dn" Hash="3930255363" />
    <Command Name="int" Hash="340908721" />
    <Command Name="staffflags" Hash="3021358894" />
    <Command Name="getstaffflags" Hash="3580006325" />
    <Command Name="nonrpname" Hash="1622484520" />
    <Command Name="setskin" Hash="934967852" />
    <Command Name="setname" Hash="1809869876" />
    <Command Name="setaccent" Hash="2041102865" />
    <Command Name="plrinfo" Hash="1743625616" />
    <Command Name="getplrhouse" Hash="2410855153" />
    <Command Name="getplrbiz" Hash="2269973052" />
    <Command Name="ip" Hash="2783163181" />
    <Command Name="plrsync" Hash="2152683965" />
    <Command Name="switchchar" Hash="925728418" />
    <Command Name="usechar" Hash="1390554915" />
    <Command Name="addtrig" Hash="2612767502" />
    <Command Name="deltrig" Hash="850336973" />
    <Command Name="deltrigcond" Hash="2326689261" />
    <Command Name="deltrigresp" Hash="2318039200" />
    <Command Name="triggers" Hash="248416589" />
    <Command Name="trigcond" Hash="3919528790" />
    <Command Name="trigtoggle" Hash="3621806868" />
    <Command Name="tempveh" Hash="3698377893" />
    <Command Name="oldcar" Hash="681236923" />
    <Command Name="lastcar" Hash="3229726539" />
    <Command Name="unlock" Hash="1793372399" />
    <Command Name="vehrespawnpublic" Hash="3922930954" />
    <Command Name="vehowner" Hash="997636202" />
    <Command Name="vehclan" Hash="1562240026" />
    <Command Name="vehbiz" Hash="2353348396" />
    <Command Name="vehrank" Hash="1251127283" />
    <Command Name="vehpark" Hash="116144677" />
    <Command Name="vehrespawnall" Hash="4068906615" />
    <Command Name="vehrespawnjob" Hash="843450194" />
    <Command Name="vehrespawnplr" Hash="359490131" />
    <Command Name="vehrespawnbiz" Hash="2036558138" />
    <Command Name="vehrespawn" Hash="2026210653" />
    <Command Name="carrespawnall" Hash="351347854" />
    <Command Name="carrespawnempty" Hash="3796941249" />
    <Command Name="carrespawnjob" Hash="3560027563" />
    <Command Name="carrespawnplr" Hash="4078620842" />
    <Command Name="carrespawnpublic" Hash="1263815958" />
    <Command Name="carrespawn" Hash="164999966" />
    <Command Name="carreloadall" Hash="1616522302" />
    <Command Name="vehrent" Hash="3230862042" />
    <Command Name="vehstoprent" Hash="3033622543" />
    <Command Name="vehbuy" Hash="4080743371" />
    <Command Name="vehcolour" Hash="249087681" />
    <Command Name="vehlivery" Hash="2590964950" />
    <Command Name="vehrepair" Hash="2059704110" />
</Commands>
